[{"id":"70-19918735242945ipl","date":"Sat, 26 Mar","team1":"Chennai Super Kings","team2":"Kolkata Knight Riders","winner":"Kolkata Knight Riders"},{"id":"533-2263580883475ipl","date":"Sun, 27 Mar","team1":"Mumbai Indians","team2":"Delhi Capitals","winner":"Delhi Capitals"},{"id":"433-319590993919ipl","date":"Sun, 27 Mar","team1":"Royal Challengers Bangalore","team2":"Punjab Kings","winner":"Punjab Kings"},{"id":"156-09045628831578ipl","date":"Mon, 28 Mar","team1":"Lucknow Super Giants","team2":"Gujarat Titans","winner":"Gujarat Titans"},{"id":"246-5633833311806ipl","date":"Tue, 29 Mar","team1":"Rajasthan Royals","team2":"Sunrisers Hyderabad","winner":"Rajasthan Royals"},{"id":"293-10081872978674ipl","date":"30 Mar","team1":"Kolkata Knight Riders","team2":"Royal Challengers Bangalore","winner":"Royal Challengers Bangalore"},{"id":"163-40752602071638ipl","date":"31 Mar","team1":"Chennai Super Kings","team2":"Lucknow Super Giants","winner":"Lucknow Super Giants"},{"id":"373-692405289327ipl","date":"1 Apr","team1":"Punjab Kings","team2":"Kolkata Knight Riders","winner":"Kolkata Knight Riders"},{"id":"407-13688112519463ipl","date":"2 Apr","team1":"Rajasthan Royals","team2":"Mumbai Indians","winner":"Rajasthan Royals"},{"id":"227-73875256240183ipl","date":"2 Apr","team1":"Gujarat Titans","team2":"Delhi Capitals","winner":"Gujarat Titans"},{"id":"96-82119924967012ipl","date":"3 Apr","team1":"Punjab Kings","team2":"Chennai Super Kings","winner":"Punjab Kings"},{"id":"99-50163698398559ipl","date":"4 Apr","team1":"Lucknow Super Giants","team2":"Sunrisers Hyderabad","winner":"Lucknow Super Giants"},{"id":"51-28046550827808ipl","date":"5 Apr","team1":"Rajasthan Royals","team2":"Royal Challengers Bangalore","winner":"Royal Challengers Bangalore"},{"id":"150-37472819079113ipl","date":"6 Apr","team1":"Mumbai Indians","team2":"Kolkata Knight Riders","winner":"Kolkata Knight Riders"},{"id":"261-43208002721576ipl","date":"7 Apr","team1":"Delhi Capitals","team2":"Lucknow Super Giants","winner":"Lucknow Super Giants"},{"id":"196-9528173474642ipl","date":"8 Apr","team1":"Punjab Kings","team2":"Gujarat Titans","winner":"Gujarat Titans"},{"id":"368-9783742548513ipl","date":"9 Apr","team1":"Chennai Super Kings","team2":"Sunrisers Hyderabad","winner":"Sunrisers Hyderabad"},{"id":"181-30679229062852ipl","date":"9 Apr","team1":"Mumbai Indians","team2":"Royal Challengers Bangalore","winner":"Royal Challengers Bangalore"},{"id":"702-2735334270177ipl","date":"10 Apr","team1":"Delhi Capitals","team2":"Kolkata Knight Riders","winner":"Delhi Capitals"},{"id":"505-4837731481489ipl","date":"10 Apr","team1":"Rajasthan Royals","team2":"Lucknow Super Giants","winner":"Rajasthan Royals"},{"id":"179-07224258082323ipl","date":"11 Apr","team1":"Gujarat Titans","team2":"Sunrisers Hyderabad","winner":"Sunrisers Hyderabad"},{"id":"14-476959714756696ipl","date":"12 Apr","team1":"Chennai Super Kings","team2":"Royal Challengers Bangalore","winner":"Chennai Super Kings"},{"id":"160-2251521234039ipl","date":"13 Apr","team1":"Punjab Kings","team2":"Mumbai Indians","winner":"Punjab Kings"},{"id":"54-13956219180492ipl","date":"14 Apr","team1":"Gujarat Titans","team2":"Rajasthan Royals","winner":"Gujarat Titans"},{"id":"5-76109265340327ipl","date":"15 Apr","team1":"Kolkata Knight Riders","team2":"Sunrisers Hyderabad","winner":"Sunrisers Hyderabad"},{"id":"141-93134913711563ipl","date":"16 Apr","team1":"Lucknow Super Giants","team2":"Mumbai Indians","winner":"Lucknow Super Giants"},{"id":"114-89417315282157ipl","date":"16 Apr","team1":"Royal Challengers Bangalore","team2":"Delhi Capitals","winner":"Royal Challengers Bangalore"},{"id":"194-60833733379835ipl","date":"17 Apr","team1":"Punjab Kings","team2":"Sunrisers Hyderabad","winner":"Sunrisers Hyderabad"},{"id":"131-99207553874433ipl","date":"17 Apr","team1":"Chennai Super Kings","team2":"Gujarat Titans","winner":"Gujarat Titans"},{"id":"490-31799255636275ipl","date":"18 Apr","team1":"Rajasthan Royals","team2":"Kolkata Knight Riders","winner":"Rajasthan Royals"},{"id":"184-21752671295377ipl","date":"19 Apr","team1":"Royal Challengers Bangalore","team2":"Lucknow Super Giants","winner":"Royal Challengers Bangalore"},{"id":"22-405995015178355ipl","date":"20 Apr","team1":"Delhi Capitals","team2":"Punjab Kings","winner":null},{"id":"224-9334499232783ipl","date":"21 Apr","team1":"Mumbai Indians","team2":"Chennai Super Kings","winner":null},{"id":"329-3118810335367ipl","date":"22 Apr","team1":"Delhi Capitals","team2":"Rajasthan Royals","winner":null},{"id":"409-21510952186827ipl","date":"23 Apr","team1":"Kolkata Knight Riders","team2":"Gujarat Titans","winner":null},{"id":"30-71881055236022ipl","date":"23 Apr","team1":"Royal Challengers Bangalore","team2":"Sunrisers Hyderabad","winner":null},{"id":"780-411723990867ipl","date":"24 Apr","team1":"Lucknow Super Giants","team2":"Mumbai Indians","winner":null},{"id":"380-7452411713899ipl","date":"25 Apr","team1":"Punjab Kings","team2":"Chennai Super Kings","winner":null},{"id":"255-58264831737665ipl","date":"26 Apr","team1":"Royal Challengers Bangalore","team2":"Rajasthan Royals","winner":null},{"id":"149-3586842565743ipl","date":"27 Apr","team1":"Gujarat Titans","team2":"Sunrisers Hyderabad","winner":null},{"id":"335-2488151098702ipl","date":"28 Apr","team1":"Delhi Capitals","team2":"Kolkata Knight Riders","winner":null},{"id":"388-3554724700217ipl","date":"29 Apr","team1":"Punjab Kings","team2":"Lucknow Super Giants","winner":null},{"id":"116-89018307721285ipl","date":"30 Apr","team1":"Gujarat Titans","team2":"Royal Challengers Bangalore","winner":null},{"id":"575-8454372895313ipl","date":"30 Apr","team1":"Rajasthan Royals","team2":"Mumbai Indians","winner":null},{"id":"446-0176538445506ipl","date":"1 May","team1":"Delhi Capitals","team2":"Lucknow Super Giants","winner":null},{"id":"110-00174751487454ipl","date":"1 May","team1":"Sunrisers Hyderabad","team2":"Chennai Super Kings","winner":null},{"id":"292-848130769893ipl","date":"2 May","team1":"Kolkata Knight Riders","team2":"Rajasthan Royals","winner":null},{"id":"408-58905206436594ipl","date":"3 May","team1":"Gujarat Titans","team2":"Punjab Kings","winner":null},{"id":"580-3069579354413ipl","date":"4 May","team1":"Royal Challengers Bangalore","team2":"Chennai Super Kings","winner":null},{"id":"12-682138467336507ipl","date":"5 May","team1":"Delhi Capitals","team2":"Sunrisers Hyderabad","winner":null},{"id":"26-8799149968318ipl","date":"6 May","team1":"Gujarat Titans","team2":"Mumbai Indians","winner":null},{"id":"144-3094628158217ipl","date":"7 May","team1":"Punjab Kings","team2":"Rajasthan Royals","winner":null},{"id":"60-43477954844002ipl","date":"7 May","team1":"Lucknow Super Giants","team2":"Kolkata Knight Riders","winner":null},{"id":"391-8792597840013ipl","date":"8 May","team1":"Sunrisers Hyderabad","team2":"Royal Challengers Bangalore","winner":null},{"id":"209-59979061501815ipl","date":"8 May","team1":"Chennai Super Kings","team2":"Delhi Capitals","winner":null},{"id":"63-124239946091826ipl","date":"9 May","team1":"Mumbai Indians","team2":"Kolkata Knight Riders","winner":null},{"id":"136-47662323071611ipl","date":"10 May","team1":"Lucknow Super Giants","team2":"Gujarat Titans","winner":null},{"id":"656-0991195894347ipl","date":"11 May","team1":"Rajasthan Royals","team2":"Delhi Capitals","winner":null},{"id":"849-917663910142ipl","date":"12 May","team1":"Chennai Super Kings","team2":"Mumbai Indians","winner":null},{"id":"271-63198547767877ipl","date":"13 May","team1":"Royal Challengers Bangalore","team2":"Punjab Kings","winner":null},{"id":"514-656278524913ipl","date":"14 May","team1":"Kolkata Knight Riders","team2":"Sunrisers Hyderabad","winner":null},{"id":"167-07530138945796ipl","date":"15 May","team1":"Chennai Super Kings","team2":"Gujarat Titans","winner":null},{"id":"352-55107852535303ipl","date":"15 May","team1":"Lucknow Super Giants","team2":"Rajasthan Royals","winner":null},{"id":"450-315895788519ipl","date":"16 May","team1":"Punjab Kings","team2":"Delhi Capitals","winner":null},{"id":"5-287742033987711ipl","date":"17 May","team1":"Mumbai Indians","team2":"Sunrisers Hyderabad","winner":null},{"id":"153-33023933817435ipl","date":"18 May","team1":"Kolkata Knight Riders","team2":"Lucknow Super Giants","winner":null},{"id":"82-16423395257041ipl","date":"19 May","team1":"Royal Challengers Bangalore","team2":"Gujarat Titans","winner":null},{"id":"6-924175714535717ipl","date":"20 May","team1":"Rajasthan Royals","team2":"Chennai Super Kings","winner":null},{"id":"55-656801061348524ipl","date":"21 May","team1":"Mumbai Indians","team2":"Delhi Capitals","winner":null},{"id":"694-3621061128941ipl","date":"22 May","team1":"Sunrisers Hyderabad","team2":"Punjab Kings","winner":null}]